demo/__init__.py
demo/fakechat_langchain.py
demo/mockgpt_langchain.py
demo/mockgpt_runnable_langchain.py
demo/openai_langchain.py
demo/fastapi_langchain/__init__.py
demo/fastapi_langchain/main.py
xpuls/__init__.py
xpuls/mlmonitor/__init__.py
xpuls/mlmonitor/langchain/__init__.py
xpuls/mlmonitor/langchain/instrument.py
xpuls/mlmonitor/langchain/xpuls_client.py
xpuls/mlmonitor/langchain/decorators/__init__.py
xpuls/mlmonitor/langchain/decorators/map_xpuls_project.py
xpuls/mlmonitor/langchain/decorators/telemetry_override_labels.py
xpuls/mlmonitor/langchain/handlers/__init__.py
xpuls/mlmonitor/langchain/handlers/callback_handlers.py
xpuls/mlmonitor/langchain/handlers/constants.py
xpuls/mlmonitor/langchain/patches/__init__.py
xpuls/mlmonitor/langchain/patches/patch_invoke.py
xpuls/mlmonitor/langchain/patches/patch_run.py
xpuls/mlmonitor/langchain/patches/utils.py
xpuls/mlmonitor/langchain/profiling/__init__.py
xpuls/mlmonitor/langchain/profiling/prometheus.py
xpuls/mlmonitor/utils/__init__.py
xpuls/mlmonitor/utils/common.py
xpuls/mlmonitor/utils/constants.py
xpuls_mlmonitor-0.2.0.dist-info/LICENSE
xpuls_mlmonitor-0.2.0.dist-info/METADATA
xpuls_mlmonitor-0.2.0.dist-info/WHEEL
xpuls_mlmonitor-0.2.0.dist-info/top_level.txt
xpuls_mlmonitor-0.2.0.dist-info/RECORD
